openeo_executor_bindings/__init__.py
openeo_executor_bindings/model.py
eodc_faas_openeo-2025.11.11.dist-info/METADATA
eodc_faas_openeo-2025.11.11.dist-info/WHEEL
eodc_faas_openeo-2025.11.11.dist-info/RECORD
