Metadata-Version: 2.1
Name: eodc-faas-openeo
Version: 2025.11.11
Summary: Bindings for the OpenEO processor exposed at EODC
Author: Lukas Weidenholzer
Author-email: lukas.weidenholzer@eodc.eu
Requires-Python: >=3.10,<3.13
Classifier: Programming Language :: Python :: 3
Classifier: Programming Language :: Python :: 3.10
Classifier: Programming Language :: Python :: 3.11
Requires-Dist: pydantic (>=2.0.0)
